LICENSE
README.md
setup.cfg
setup.py
tonetext/__init__.py
tonetext/color_print.py
tonetext/colors.py
tonetext/specials.py
tonetext/terminals.py
tonetext/utils.py
tonetext.egg-info/PKG-INFO
tonetext.egg-info/SOURCES.txt
tonetext.egg-info/dependency_links.txt
tonetext.egg-info/top_level.txt